{
  "pageTitleShort": "เพิ่มการมองเห็นข้อมูลคงคลังด้วยชั้น Monitoring",
  "heroTitle": "ทำให้ข้อมูลคงคลังมองเห็นได้จริง: เสริมชั้น Monitoring เพื่อทำให้การเก็บข้อมูล 80 สาขาเสถียร",
  "backLabel": "กลับไปหน้ากรณีศึกษาทั้งหมด",
  "breadcrumbs": {
    "home": "หน้าแรก",
    "hub": "กรณีศึกษา",
    "current": "เพิ่มการมองเห็นข้อมูลคงคลังด้วยชั้น Monitoring"
  },
  "sections": [
    {
      "id": "snapshot",
      "heading": "ภาพรวม",
      "blocks": [
        {
          "type": "p",
          "text": "โครงการนี้เน้นสร้าง visibility ต่อสถานะข้อมูลคงคลังจากหลายสาขาให้ทีมปฏิบัติการเห็นปัญหาได้ก่อนกระทบธุรกิจ"
        }
      ]
    },
    {
      "id": "the-challenge",
      "heading": "ความท้าทาย",
      "blocks": [
        {
          "type": "p",
          "text": "ระบบเก็บข้อมูลคงคลังจากหลายสาขาทำงานได้ แต่ขาดมุมมองรวมและสัญญาณเตือนที่เชื่อถือได้"
        },
        {
          "type": "p",
          "text": "ลูกค้าต้องการระบบที่บอกสถานะจริงได้ทันเวลาและแปลงเป็นการตัดสินใจเชิงปฏิบัติการได้"
        },
        {
          "type": "list",
          "items": [
            "ทีมส่วนกลางเห็นปัญหาช้า เพราะไม่มีภาพรวมสถานะข้อมูลแบบเดียวกัน",
            "เหตุผิดปกติจากแต่ละสาขาถูกค้นพบเมื่อผลกระทบเกิดแล้ว",
            "การไล่หาสาเหตุทำได้ยากเพราะข้อมูลกระจายหลายจุด"
          ]
        },
        {
          "type": "p",
          "text": "ลูกค้าต้องการระบบที่บอกสถานะจริงได้ทันเวลาและแปลงเป็นการตัดสินใจเชิงปฏิบัติการได้"
        }
      ]
    },
    {
      "id": "constraints",
      "heading": "ข้อจำกัด",
      "blocks": [
        {
          "type": "list",
          "items": [
            "ต้องเสริมบนระบบเดิมโดยไม่รบกวนการดำเนินงานประจำ",
            "แต่ละสาขามีคุณภาพข้อมูลและสภาพแวดล้อมต่างกัน",
            "ต้องลด false alarm เพื่อไม่ให้ทีมเพิกเฉยต่อแจ้งเตือน"
          ]
        }
      ]
    },
    {
      "id": "approach",
      "heading": "แนวทางดำเนินการ",
      "blocks": [
        {
          "type": "p",
          "text": "กำหนด signal สำคัญที่สะท้อนความเสี่ยงทางธุรกิจจริงของข้อมูลคงคลัง"
        },
        {
          "type": "p",
          "text": "สร้าง monitoring layer ที่รวมสถานะ ingestion, validation และ freshness"
        },
        {
          "type": "ordered",
          "items": [
            "ยกระดับการตรวจจับปัญหาแบบ proactive ก่อนกระทบธุรกิจ",
            "ลดเวลาไล่สาเหตุด้วยข้อมูลที่เชื่อมโยงกัน",
            "ทำให้การสื่อสารสถานะเป็นภาษาที่ทั้งเทคนิคและธุรกิจเข้าใจตรงกัน"
          ]
        },
        {
          "type": "p",
          "text": "ออกแบบ dashboard สำหรับทีมเทคนิคและทีมธุรกิจโดยใช้ตัวชี้วัดชุดเดียวกัน"
        },
        {
          "type": "p",
          "text": "กำหนด alert threshold ตามบริบทสาขาและความรุนแรงของเหตุ"
        },
        {
          "type": "p",
          "text": "ทำ incident workflow จาก alert ไปจนถึงการยืนยันการแก้ไข"
        },
        {
          "type": "ordered",
          "items": [
            "ยกระดับการตรวจจับปัญหาแบบ proactive ก่อนกระทบธุรกิจ",
            "ลดเวลาไล่สาเหตุด้วยข้อมูลที่เชื่อมโยงกัน",
            "ทำให้การสื่อสารสถานะเป็นภาษาที่ทั้งเทคนิคและธุรกิจเข้าใจตรงกัน",
            "ทำให้การสื่อสารสถานะเป็นภาษาที่ทั้งเทคนิคและธุรกิจเข้าใจตรงกัน",
            "ทำให้การสื่อสารสถานะเป็นภาษาที่ทั้งเทคนิคและธุรกิจเข้าใจตรงกัน",
            "ทำให้การสื่อสารสถานะเป็นภาษาที่ทั้งเทคนิคและธุรกิจเข้าใจตรงกัน"
          ]
        },
        {
          "type": "p",
          "text": "ปรับปรุง logging และ correlation เพื่อสืบค้น root cause ได้เร็ว"
        }
      ]
    },
    {
      "id": "what-was-delivered",
      "heading": "สิ่งที่ส่งมอบ",
      "blocks": [
        {
          "type": "list",
          "items": [
            "monitoring layer สำหรับกระบวนการข้อมูลคงคลังหลายสาขา",
            "dashboard สถานะและ quality indicator ที่ใช้ร่วมกัน",
            "ระบบแจ้งเตือนพร้อมระดับความรุนแรงและแนวทางตอบสนอง",
            "ปรับปรุง logging/correlation สำหรับ root-cause analysis",
            "เอกสารปฏิบัติการและการส่งมอบให้ทีมภายใน"
          ]
        }
      ]
    },
    {
      "id": "results",
      "heading": "ผลลัพธ์",
      "blocks": [
        {
          "type": "list",
          "items": [
            "ทีมตรวจพบความผิดปกติได้เร็วขึ้นก่อนเกิดผลกระทบวงกว้าง",
            "เวลาแก้ไขเหตุการณ์ข้อมูลคงคลังสั้นลงอย่างต่อเนื่อง",
            "ลดเหตุซ้ำจากจุดเดิมด้วยการปิด root cause อย่างเป็นระบบ",
            "คุณภาพข้อมูลคงคลังมีเสถียรภาพมากขึ้นระหว่างสาขา",
            "ผู้บริหารมีมุมมองสถานะที่ชัดเจนสำหรับการตัดสินใจ"
          ]
        }
      ]
    },
    {
      "id": "why-it-worked",
      "heading": "เหตุผลที่แนวทางนี้ได้ผล",
      "blocks": [
        {
          "type": "p",
          "text": "แนวทางนี้ได้ผลเพราะเริ่มจากผลกระทบทางธุรกิจจริงและเลือกแก้จุดคอขวดที่สำคัญก่อน"
        },
        {
          "type": "p",
          "text": "การตัดสินใจเชิงเทคนิคถูกกำหนดด้วยข้อจำกัดหน้างานจริง ไม่ใช่สมมติฐานเชิงทฤษฎี"
        },
        {
          "type": "p",
          "text": "มีตัวชี้วัดและจุดตรวจสอบที่ชัดเจน ทำให้ลดความเสี่ยงระหว่างการเปลี่ยนแปลง"
        }
      ]
    },
    {
      "id": "how-vionix-worked",
      "heading": "วิธีที่ Vionix ทำงานร่วมกับทีมลูกค้า",
      "blocks": [
        {
          "type": "list",
          "items": [
            "สัปดาห์ที่ 1: วิเคราะห์สภาพจริงและจัดลำดับความสำคัญของปัญหา",
            "สัปดาห์ที่ 2: ลงมือแก้จุดคอขวดหลักและทดสอบกับสถานการณ์ใช้งานจริง",
            "สัปดาห์ที่ 3: ติดตามผล ปรับจูน และส่งมอบความรู้ให้ทีมภายใน"
          ]
        }
      ]
    }
  ],
  "cta": {
    "title": "มีความท้าทายลักษณะเดียวกันหรือไม่",
    "copy": "แจ้งคอขวดหลัก แรงกดดันทางธุรกิจ และเทคสแตกปัจจุบันให้เรา เพื่อรับข้อเสนอขั้นแรกที่ชัดเจนและนำไปใช้งานได้ทันที",
    "button": "ติดต่อ Vionix",
    "href": "index.html#contact"
  }
}
