{
  "pageTitleShort": "ทำระบบ ERP อายุ 30 ปีให้กลับมาควบคุมได้โดยไม่ต้องรื้อใหม่",
  "heroTitle": "จากความโกลาหลสู่การควบคุม: ทำ ERP อายุ 30 ปีให้เสถียรโดยไม่ต้องเขียนใหม่",
  "backLabel": "กลับไปหน้ากรณีศึกษาทั้งหมด",
  "breadcrumbs": {
    "home": "หน้าแรก",
    "hub": "กรณีศึกษา",
    "current": "ทำระบบ ERP อายุ 30 ปีให้กลับมาควบคุมได้โดยไม่ต้องรื้อใหม่"
  },
  "sections": [
    {
      "id": "snapshot",
      "heading": "ภาพรวม",
      "blocks": [
        {
          "type": "p",
          "text": "องค์กรพึ่งพา ERP เดิมมานานหลายทศวรรษจนเกิดความซับซ้อนสะสมและความเสี่ยงเชิงปฏิบัติการสูง"
        },
        {
          "type": "p",
          "text": "โครงการนี้เน้นควบคุมความเสี่ยงและเสถียรภาพโดยใช้แนวทางปรับปรุงเป็นขั้นตอน แทนการรีไรต์ทั้งระบบ"
        }
      ]
    },
    {
      "id": "the-challenge",
      "heading": "ความท้าทาย",
      "blocks": [
        {
          "type": "p",
          "text": "ปัญหาเกิดทั้งด้านเทคนิค กระบวนการ และการตัดสินใจ เพราะไม่มีภาพรวมระบบที่ชัดเจน"
        },
        {
          "type": "p",
          "text": "โจทย์จริงคือฟื้นการควบคุมระบบและลดความเปราะบางแบบวัดผลได้ในทุกระยะ"
        }
      ]
    },
    {
      "id": "constraints",
      "heading": "ข้อจำกัด",
      "blocks": [
        {
          "type": "p",
          "text": "โครงการต้องเดินหน้าภายใต้ข้อจำกัดของระบบเดิมและหน้าต่างเวลาปฏิบัติการที่จำกัด"
        },
        {
          "type": "p",
          "text": "แนวทางที่เลือกต้องลดความเสี่ยงได้เร็วและไม่รบกวนงานหลักขององค์กร"
        },
        {
          "type": "p",
          "text": "ทุกการเปลี่ยนแปลงต้องส่งมอบให้ทีมภายในดูแลต่อได้อย่างยั่งยืน"
        },
        {
          "type": "p",
          "text": "ทุกการเปลี่ยนแปลงต้องส่งมอบให้ทีมภายในดูแลต่อได้อย่างยั่งยืน"
        }
      ]
    },
    {
      "id": "approach",
      "heading": "แนวทางดำเนินการ",
      "blocks": [
        {
          "type": "p",
          "text": "ทำระบบแผนที่การพึ่งพาโมดูลเพื่อเห็นจุดเสี่ยงเชิงโครงสร้าง"
        },
        {
          "type": "p",
          "text": "จัดลำดับงาน stabilisation ตาม business criticality และความน่าจะเป็นของ incident"
        },
        {
          "type": "p",
          "text": "แยก quick wins ที่ลดความเสี่ยงทันทีออกจากงานเชิงโครงสร้างระยะกลาง"
        },
        {
          "type": "p",
          "text": "ปรับกระบวนการ release/change ให้มี quality gate ที่ชัดเจน"
        },
        {
          "type": "p",
          "text": "เพิ่ม observability ในจุดที่เคยเป็น blind spot"
        },
        {
          "type": "p",
          "text": "ทำมาตรฐาน incident review และ knowledge capture หลังเหตุการณ์"
        },
        {
          "type": "p",
          "text": "ลด technical debt ในจุดคอขวดที่กระทบหลายโมดูลพร้อมกัน"
        }
      ]
    },
    {
      "id": "what-was-delivered",
      "heading": "สิ่งที่ส่งมอบ",
      "blocks": [
        {
          "type": "list",
          "items": [
            "แผน stabilisation ERP แบบหลายระยะพร้อม priority ที่ชัดเจน",
            "มาตรฐาน change/release และ incident review ใหม่",
            "ปรับปรุง observability ในโมดูลสำคัญ",
            "เอกสาร dependency และความเสี่ยงเชิงระบบ",
            "โครงสร้าง handover ให้ทีมภายในดูแลต่อได้",
            "โครงสร้าง handover ให้ทีมภายในดูแลต่อได้"
          ]
        }
      ]
    },
    {
      "id": "results",
      "heading": "ผลลัพธ์",
      "blocks": [
        {
          "type": "p",
          "text": "ผลลัพธ์เกิดทั้งด้านประสิทธิภาพระบบและความคล่องตัวของการทำงานร่วมกันระหว่างทีม"
        },
        {
          "type": "p",
          "text": "ความเสถียรที่เพิ่มขึ้นช่วยลดงานแก้ปัญหาเฉพาะหน้าและเพิ่มเวลาให้ทีมโฟกัสงานเชิงคุณค่า"
        },
        {
          "type": "p",
          "text": "ผู้มีส่วนได้ส่วนเสียสามารถตัดสินใจจากข้อมูลที่เชื่อถือได้มากขึ้น"
        },
        {
          "type": "p",
          "text": "ผู้มีส่วนได้ส่วนเสียสามารถตัดสินใจจากข้อมูลที่เชื่อถือได้มากขึ้น"
        },
        {
          "type": "p",
          "text": "ผู้มีส่วนได้ส่วนเสียสามารถตัดสินใจจากข้อมูลที่เชื่อถือได้มากขึ้น"
        }
      ]
    },
    {
      "id": "why-it-worked",
      "heading": "เหตุผลที่แนวทางนี้ได้ผล",
      "blocks": [
        {
          "type": "p",
          "text": "แนวทางนี้ได้ผลเพราะเริ่มจากผลกระทบทางธุรกิจจริงและเลือกแก้จุดคอขวดที่สำคัญก่อน"
        },
        {
          "type": "p",
          "text": "การตัดสินใจเชิงเทคนิคถูกกำหนดด้วยข้อจำกัดหน้างานจริง ไม่ใช่สมมติฐานเชิงทฤษฎี"
        },
        {
          "type": "p",
          "text": "มีตัวชี้วัดและจุดตรวจสอบที่ชัดเจน ทำให้ลดความเสี่ยงระหว่างการเปลี่ยนแปลง"
        },
        {
          "type": "p",
          "text": "รูปแบบการทำงานร่วมกับทีมลูกค้าทำให้รักษาผลลัพธ์ได้หลังส่งมอบ"
        }
      ]
    },
    {
      "id": "how-vionix-worked",
      "heading": "วิธีที่ Vionix ทำงานร่วมกับทีมลูกค้า",
      "blocks": [
        {
          "type": "p",
          "text": "Vionix ทำงานร่วมกับทีมลูกค้าเป็นรอบสั้น พร้อมเป้าหมายรายช่วงและเกณฑ์ยืนยันผลที่ชัดเจน"
        }
      ]
    }
  ],
  "cta": {
    "title": "มีความท้าทายลักษณะเดียวกันหรือไม่",
    "copy": "แจ้งคอขวดหลัก แรงกดดันทางธุรกิจ และเทคสแตกปัจจุบันให้เรา เพื่อรับข้อเสนอขั้นแรกที่ชัดเจนและนำไปใช้งานได้ทันที",
    "button": "ติดต่อ Vionix",
    "href": "index.html#contact"
  }
}
